conctx/__init__.py
conctx/conctx.py
dkamotsky.conctx-1.0.2.dist-info/DESCRIPTION.rst
dkamotsky.conctx-1.0.2.dist-info/LICENSE.txt
dkamotsky.conctx-1.0.2.dist-info/METADATA
dkamotsky.conctx-1.0.2.dist-info/RECORD
dkamotsky.conctx-1.0.2.dist-info/WHEEL
dkamotsky.conctx-1.0.2.dist-info/metadata.json
dkamotsky.conctx-1.0.2.dist-info/top_level.txt
